{
	"required": true,
	"package": "fi.dy.masa.tweakaforknomore.mixin",
	"minVersion": "0.8",
	"compatibilityLevel": "JAVA_17",
	"client": [
		"MixinAbstractDecorationEntity",
		"MixinChestBlock",
		"MixinClientPlayNetworkHandler",
		"MixinClientPlayerEntity",
		"MixinClientPlayerInteractionManager",
		"MixinClientWorldProperties",
		"MixinEntity",
		"MixinEntityRenderDispatcher",
		"MixinEntityRenderer",
		"MixinInputUtil",
		"MixinLevelProperties",
		"MixinMinecraftClient",
		"MixinPistonBlock",
		"MixinPistonBlock_eventTracker",
		"MixinSignEditScreen",
		"MixinStructureBlockBlockEntityRenderer",
		"MixinWidgetConfigOptionBase",
		"MixinWindow",
		"MixinWorld",
		"MixinWorldRenderer"
    ],
	"mixinPriority": 990,
	"injectors": {
		"defaultRequire": 0
	}
}
